<?xml version="1.0" encoding="UTF-8"?>
<MetaDataObject xmlns="http://v8.1c.ru/8.3/MDClasses" xmlns:app="http://v8.1c.ru/8.2/managed-application/core" xmlns:cfg="http://v8.1c.ru/8.1/data/enterprise/current-config" xmlns:cmi="http://v8.1c.ru/8.2/managed-application/cmi" xmlns:ent="http://v8.1c.ru/8.1/data/enterprise" xmlns:lf="http://v8.1c.ru/8.2/managed-application/logform" xmlns:style="http://v8.1c.ru/8.1/data/ui/style" xmlns:sys="http://v8.1c.ru/8.1/data/ui/fonts/system" xmlns:v8="http://v8.1c.ru/8.1/data/core" xmlns:v8ui="http://v8.1c.ru/8.1/data/ui" xmlns:web="http://v8.1c.ru/8.1/data/ui/colors/web" xmlns:win="http://v8.1c.ru/8.1/data/ui/colors/windows" xmlns:xen="http://v8.1c.ru/8.3/xcf/enums" xmlns:xpr="http://v8.1c.ru/8.3/xcf/predef" xmlns:xr="http://v8.1c.ru/8.3/xcf/readable" xmlns:xs="http://www.w3.org/2001/XMLSchema" xmlns:xsi="http://www.w3.org/2001/XMLSchema-instance" version="2.16">
	<FunctionalOption uuid="e60e4147-9819-42e4-91b1-f0c4b49e6e07">
		<Properties>
			<Name>ИспользоватьПартнеров</Name>
			<Synonym>
				<v8:item>
					<v8:lang>ru</v8:lang>
					<v8:content>Использовать партнеров</v8:content>
				</v8:item>
			</Synonym>
			<Comment/>
			<Location>Constant.ИспользоватьПартнеров</Location>
			<PrivilegedGetMode>true</PrivilegedGetMode>
			<Content>
				<xr:Object>Catalog.Партнеры</xr:Object>
				<xr:Object>Document.ПоступлениеТоваров.Attribute.Партнер</xr:Object>
				<xr:Object>Document.ЗаказПоставщику.Attribute.Партнер</xr:Object>
				<xr:Object>Document.СпецификацияКДоговору.Attribute.Партнер</xr:Object>
				<xr:Object>Document.ВозвратТоваровПоставщику.Attribute.Партнер</xr:Object>
			</Content>
		</Properties>
	</FunctionalOption>
</MetaDataObject>